SnapMem/__init__.py
snapmem-0.0.1.dist-info/METADATA
snapmem-0.0.1.dist-info/WHEEL
snapmem-0.0.1.dist-info/top_level.txt
snapmem-0.0.1.dist-info/RECORD
