Metadata-Version: 2.4
Name: snapmem
Version: 0.0.1
Summary: Snap Memory.
Requires-Python: >=3.8
